dio-desafio-pacote-processamento-imagem/__init__.py
dio-desafio-pacote-processamento-imagem/processamento/__init__.py
dio-desafio-pacote-processamento-imagem/processamento/combinar.py
dio-desafio-pacote-processamento-imagem/processamento/transformar.py
dio-desafio-pacote-processamento-imagem/utilidades/__init__.py
dio-desafio-pacote-processamento-imagem/utilidades/io.py
dio-desafio-pacote-processamento-imagem/utilidades/plot.py
dio_proj_charles_processamento_imagem/__init__.py
dio_proj_charles_processamento_imagem/processamento/__init__.py
dio_proj_charles_processamento_imagem/processamento/combinar.py
dio_proj_charles_processamento_imagem/processamento/transformar.py
dio_proj_charles_processamento_imagem/utilidades/__init__.py
dio_proj_charles_processamento_imagem/utilidades/io.py
dio_proj_charles_processamento_imagem/utilidades/plot.py
processamento_imagem/__init__.py
processamento_imagem/processamento/__init__.py
processamento_imagem/processamento/combinar.py
processamento_imagem/processamento/transformar.py
processamento_imagem/utilidades/__init__.py
processamento_imagem/utilidades/io.py
processamento_imagem/utilidades/plot.py
dio_desafio_pacote_processamento_imagem-0.0.10.dist-info/METADATA
dio_desafio_pacote_processamento_imagem-0.0.10.dist-info/WHEEL
dio_desafio_pacote_processamento_imagem-0.0.10.dist-info/top_level.txt
dio_desafio_pacote_processamento_imagem-0.0.10.dist-info/RECORD
