Metadata-Version: 2.1
Name: dio-desafio-pacote-processamento-imagem
Version: 0.0.10
Summary: Processamento imagem usando Skimage
Home-page: https://github.com/charlesfsouza/dio-desafio-pacote-processamento-imagem
Author: Charles
License: UNKNOWN
Platform: UNKNOWN
Requires-Python: >=3.5
Requires-Dist: matplotlib (>=3.2.2)
Requires-Dist: numpy (>=1.19.3)
Requires-Dist: scikit-image (>=0.16.1)
